{"_doNotEdit":"run pnpm readme to regenerate; pnpm computed:check to verify","_generated":"src/readme/index.ts","atomPath":"paganism","bondsIn":0,"bondsOut":0,"boundaryUuid":"0bd55661-1265-89d8-ac1d-6262aa4ccf1e","computationUuid":"5e7d2f61-d00c-8365-9efc-40fd63a19cd9","contentUuid":"6177a2fd-1bed-8af9-84b9-96c9c489e102","escapes":[],"exports":["paganism"],"folded":false,"horo":null,"imports":["archangel","balance","cycle","diamond","fire","fractal","gift","holographic","identity","law","merge","name","one","part","religion","ritual","sacred","society","translator","uuid","water","wheel","whole"],"kind":"atom","links":["archangel","balance","cycle","diamond","fire","fractal","gift","holographic","identity","law","merge","name","one","part","religion","ritual","sacred","society","translator","uuid","water","wheel","whole"],"linksResolved":60,"linksTotal":60,"measure":null,"stages":[{"stage":"path","stageUuid":"29a21ae9-4eb8-8176-8b96-3fae978ab4c6"},{"stage":"trinity","stageUuid":"27041d62-5e61-8a8d-9ebf-5fc5e35c5347"},{"stage":"boundary","stageUuid":"b1717d95-9c43-8763-9ce3-04c40eade153"},{"stage":"links","stageUuid":"efe1820a-940f-846d-a26f-071776b309c3"},{"stage":"horo","stageUuid":"70673e22-6dbe-8642-a5c6-af146d4c0438"},{"stage":"seal","stageUuid":"d437d6bd-d691-8099-8ef0-8f8251a98b0d"},{"stage":"uuid","stageUuid":"2d305d35-2467-811b-97aa-fee99809a32f"}],"trinity":{"code":0,"form":1,"proof":0}}
