{"_doNotEdit":"run pnpm readme to regenerate; pnpm computed:check to verify","_generated":"src/readme/index.ts","atomPath":"bank/accounts/payroll/runs","bondsIn":22,"bondsOut":25,"boundaryUuid":"580005e3-30f4-86a6-8087-68d1126e7f6d","computationUuid":"d0482d0d-0ec1-8e29-80fd-0d97481ffeb8","contentUuid":"e91c2f81-2635-84a5-b4ef-4da4265eb704","escapes":[],"exports":["default"],"folded":true,"horo":7,"imports":["@/audit/trail/after/change","@/auth","@/auto/populate/created/by","@/auto/populate/tenant","@/auto/set/timestamp","@/base/accounting/field","@/enforce/segregation/of/duty","@/utility"],"kind":"atom","links":["accounting","adjustments","balance","centers","close","employees","entries","entry","give","horo","identity","party","privilege","proof","runs","transaction"],"linksResolved":24,"linksTotal":24,"measure":"descent","stages":[{"stage":"path","stageUuid":"e00cdde0-106c-8683-98dd-e7a809314746"},{"stage":"trinity","stageUuid":"8c600bd2-ad27-8552-a5ba-49fb69940703"},{"stage":"boundary","stageUuid":"a946f220-84a7-87f8-bbab-6129dd56d4cc"},{"stage":"links","stageUuid":"dc485665-41d9-8d5c-a6f4-57fd5be60fe6"},{"stage":"horo","stageUuid":"1309f468-8156-8987-8ebb-ed422e637ade"},{"stage":"seal","stageUuid":"74143566-4348-8b45-a1d7-072cfcf61520"},{"stage":"uuid","stageUuid":"430140f6-d8e6-8696-bc83-b15dc0ee475d"}],"trinity":{"code":1,"form":1,"proof":1}}
