{"_doNotEdit":"run pnpm readme to regenerate; pnpm computed:check to verify","_generated":"src/readme/index.ts","atomPath":"ai/industry","bondsIn":20,"bondsOut":21,"boundaryUuid":"1419d023-4718-8c52-985e-21600d5ddac0","computationUuid":"74e0fc37-d046-852f-8626-5074dcbc1cff","contentUuid":"377d4a34-4bd9-86f5-9e0c-0d608881ea03","escapes":[],"exports":["AiIndustryProblem","RemedyCoverage","const","function","interface"],"folded":true,"horo":4,"imports":["@/agent/sync","@/ai","@/integrity","@/memory/session","@/receipt","@/sandbox"],"kind":"atom","links":["ai","architecture","chat","confirm","diamond","horo","identity","law","mcp","merge","receipt","sandbox","seal","self","session","suggestions","thought","uuid"],"linksResolved":40,"linksTotal":40,"measure":"weave","stages":[{"stage":"path","stageUuid":"bf8c81db-dabb-81a4-9ea7-d9b8b7a0a33b"},{"stage":"trinity","stageUuid":"041efa57-9c75-80eb-b451-12bf8099d014"},{"stage":"boundary","stageUuid":"b76db58f-1465-80e5-9023-6077d4a2872c"},{"stage":"links","stageUuid":"b67af4e5-f8b5-8d87-a510-8cce184250ee"},{"stage":"horo","stageUuid":"d3773c05-5382-823a-863a-5c1b9a14fe89"},{"stage":"seal","stageUuid":"59a3b14f-c480-8bdc-a793-86411c4bae5e"},{"stage":"uuid","stageUuid":"ff48a281-be35-887e-8e8f-8b7bb870ee5a"}],"trinity":{"code":1,"form":1,"proof":1}}
