{"_doNotEdit":"run pnpm readme to regenerate; pnpm computed:check to verify","_generated":"src/readme/index.ts","atomPath":"kabbalah","bondsIn":17,"bondsOut":17,"boundaryUuid":"01078282-b83e-80a5-8aa9-f9d83f501833","computationUuid":"dce6baac-fce1-8c32-a00b-27ec18138d5c","contentUuid":"acb00b68-ed4b-8fd6-98bd-c578edebd580","escapes":[],"exports":["kabbalah"],"folded":true,"horo":8,"imports":["archangel","diamond","identity","judaism","law","matrix","merge","name","religion","sacred","self","society","translator","uuid","void","whole","word"],"kind":"atom","links":["archangel","diamond","identity","judaism","law","matrix","merge","name","religion","sacred","self","society","translator","uuid","void","whole","word"],"linksResolved":47,"linksTotal":47,"measure":"crest","stages":[{"stage":"path","stageUuid":"cb7c9a0e-8448-85e0-8474-6cb234c2da9f"},{"stage":"trinity","stageUuid":"d3931506-d5c2-8f6e-bef0-8534da19f021"},{"stage":"boundary","stageUuid":"1ac19068-87c5-8155-b416-33032bcb8442"},{"stage":"links","stageUuid":"b7fca7a2-3f4b-80c9-89c7-5a15b96d87d7"},{"stage":"horo","stageUuid":"30b0b8d2-4147-82da-95c5-5efbc55604f0"},{"stage":"seal","stageUuid":"1abd0f03-f79e-8fdb-8c5c-aec5bae6ca42"},{"stage":"uuid","stageUuid":"22dd6d60-d936-883f-b974-5de071cf452d"}],"trinity":{"code":0,"form":1,"proof":0}}
