{"_doNotEdit":"run pnpm readme to regenerate; pnpm computed:check to verify","_generated":"src/readme/index.ts","atomPath":"plugin","bondsIn":11,"bondsOut":11,"boundaryUuid":"972f065f-f33e-8545-9de0-d2f78042dc03","computationUuid":"2a9ec92d-1324-8e8d-9c00-c30c27375240","contentUuid":"683c3d66-120c-8c4d-8356-cceaf2fd0c15","escapes":[],"exports":["DIMENSIONAL_PLUGINS","DimensionId","DimensionalCoverageResult","DimensionalPlugin","checkDimensionalCoverage","dimensionForCollection","totalCollectionCount"],"folded":true,"horo":8,"imports":[],"kind":"atom","links":["balance","diamond","hooks","law","payload","platform","plugin","plugins","pwa","vitepress","worker"],"linksResolved":22,"linksTotal":22,"measure":"crest","stages":[{"stage":"path","stageUuid":"6759ee9d-26e8-8a92-8233-cd3bf0079ee4"},{"stage":"trinity","stageUuid":"cabba6b5-28a2-8a1a-aa8d-e731e6effc1d"},{"stage":"boundary","stageUuid":"5ad7516a-3b13-842d-955e-4dadbaed6666"},{"stage":"links","stageUuid":"b4b06795-c089-8207-bcc4-564080b9de30"},{"stage":"horo","stageUuid":"3932a1e5-78ae-8eb2-b5e9-3c7d8c4a6099"},{"stage":"seal","stageUuid":"43b86f87-1106-8e2a-a706-dd1cf130f989"},{"stage":"uuid","stageUuid":"1c3091f5-f5a4-824b-bf95-d527b1bbde65"}],"trinity":{"code":1,"form":1,"proof":1}}
