{"_doNotEdit":"run pnpm readme to regenerate; pnpm computed:check to verify","_generated":"src/readme/index.ts","atomPath":"business","bondsIn":22,"bondsOut":22,"boundaryUuid":"50fe359c-0894-8f5d-a1cf-8ae6845b62cb","computationUuid":"a66be523-7399-8ff9-b1c8-f9598b617645","contentUuid":"50fd9ac2-4d7d-8ae1-a6e5-4ef67dd0fd88","escapes":[],"exports":["business"],"folded":true,"horo":5,"imports":["audience","automotive","beauty","collapse","construction","days","entertainment","entity","event","function","health","home","hvac","law","local","lodging","medical","merge","online","sti","type"],"kind":"atom","links":["audience","automotive","beauty","collapse","construction","days","entertainment","entity","event","function","health","home","hvac","law","local","lodging","medical","merge","online","sti","type"],"linksResolved":21,"linksTotal":21,"measure":"round","stages":[{"stage":"path","stageUuid":"e068e9e6-5ad2-8891-bc0e-117d3a7eabd3"},{"stage":"trinity","stageUuid":"5d64533e-809d-8e54-9371-fc1cd8ecab8e"},{"stage":"boundary","stageUuid":"1b366748-6d5b-8e77-80c9-063edb78ab02"},{"stage":"links","stageUuid":"266b391e-0116-890b-8513-4faf7a575a75"},{"stage":"horo","stageUuid":"f7a0eec1-4bd9-8379-affe-46646976d5a8"},{"stage":"seal","stageUuid":"1a79542e-05ae-8bb4-81e7-342d0347bc49"},{"stage":"uuid","stageUuid":"cd9988e9-01f4-8455-87c5-fa5b9f884457"}],"trinity":{"code":0,"form":1,"proof":0}}
