{"_doNotEdit":"run pnpm readme to regenerate; pnpm computed:check to verify","_generated":"src/readme/index.ts","atomPath":"seed","bondsIn":73,"bondsOut":74,"boundaryUuid":"af8038af-3aaf-8a4b-94a2-ba9cd0841b05","computationUuid":"d611ebaf-2d79-8e20-934f-3fcbd1f27541","contentUuid":"b5cbc993-ced1-86e9-b052-31d8e24855b1","escapes":[],"exports":["const"],"folded":true,"horo":1,"imports":["@/error"],"kind":"atom","links":["accounting","akashic","aura","code","crop","currency","fractal","holographic","identity","items","law","localize","manufacturing","measure","organic","planting","propagation","standard","transplant","variant","version"],"linksResolved":35,"linksTotal":35,"measure":"base","stages":[{"stage":"path","stageUuid":"05e41cf0-e2fd-8003-93b3-15cc1f45e459"},{"stage":"trinity","stageUuid":"6717f03c-19f4-8c0d-8225-6e9b6e649b83"},{"stage":"boundary","stageUuid":"2d9e3b1c-18ab-85fa-ada6-6413c9e9f5d3"},{"stage":"links","stageUuid":"00c07e1c-d9ad-8ec0-9542-894b1e98bc06"},{"stage":"horo","stageUuid":"fd546583-6b8c-884c-91ca-3b2598f4b71a"},{"stage":"seal","stageUuid":"db2dbc3f-0ffd-8b47-accd-6a6a18356632"},{"stage":"uuid","stageUuid":"013810df-3f90-88d0-b47f-b73bce8ebff3"}],"trinity":{"code":1,"form":1,"proof":0}}
