{"_doNotEdit":"run pnpm readme to regenerate; pnpm computed:check to verify","_generated":"src/readme/index.ts","atomPath":"horo","bondsIn":30,"bondsOut":31,"boundaryUuid":"d9405f16-f225-8313-b871-1fad0192d3f4","computationUuid":"5844001f-4465-8ea9-946c-d550f6fc95bc","contentUuid":"55483615-d4aa-8ee6-b56b-bb61a770850a","escapes":[],"exports":["HoroStep","const","function","interface"],"folded":true,"horo":7,"imports":[],"kind":"atom","links":["access","aura","auth","balance","base","begin","close","cmyk","coil","config","crest","descent","flow","fractal","harmony","hooks","identity","integrity","law","merge","notes","one","polarity","profane","reverse","rodin","round","routing","sacred","sequence","share","society","tags","unity","uuid","weave","workflow"],"linksResolved":63,"linksTotal":63,"measure":"descent","stages":[{"stage":"path","stageUuid":"39aff5d2-1a4b-8cb1-a272-e6949b4e41b7"},{"stage":"trinity","stageUuid":"71f2bcb6-fb68-85cd-8d13-50626bb16755"},{"stage":"boundary","stageUuid":"58a2df3d-ec96-8323-9966-329c8cd7db7d"},{"stage":"links","stageUuid":"cabf2fd5-51c4-89fc-ae9b-ba9c7ef0d52e"},{"stage":"horo","stageUuid":"2ac906a8-5cb1-879e-a4df-4942749439b3"},{"stage":"seal","stageUuid":"c34ca3f7-30b4-8344-b915-74b137c9a3f3"},{"stage":"uuid","stageUuid":"3ba18bfc-7863-83c0-aece-c66dd306fd52"}],"trinity":{"code":1,"form":1,"proof":1}}
