{"_doNotEdit":"run pnpm readme to regenerate; pnpm computed:check to verify","_generated":"src/readme/index.ts","atomPath":"mortality","bondsIn":15,"bondsOut":15,"boundaryUuid":"5ce4dd0a-5110-8dfd-9ead-dac9fb506c6c","computationUuid":"0ffa3644-2bfd-846e-bf8e-4c14084ecddf","contentUuid":"1022f26d-5b65-816d-8fdd-8da206220809","escapes":[],"exports":["mortality"],"folded":true,"horo":5,"imports":["animal","apiculture","aquaculture","biological","biomass","entry","forestry","health","law","livestock","rate","risk","scouting","yield"],"kind":"atom","links":["animal","apiculture","aquaculture","assets","biomass","entry","forestry","health","law","livestock","rate","risk","scouting","yield"],"linksResolved":27,"linksTotal":27,"measure":"round","stages":[{"stage":"path","stageUuid":"f451b4d7-2522-8f46-953e-6128eb45fe16"},{"stage":"trinity","stageUuid":"79ca4e0e-6c8b-82f7-b358-972748707833"},{"stage":"boundary","stageUuid":"694d0f10-05e6-827f-99be-384adbc58ba7"},{"stage":"links","stageUuid":"e1b700b9-bf61-8d53-bd89-b7596f7d050b"},{"stage":"horo","stageUuid":"f599f1b1-2a78-8b11-b27f-bb454a1b30a9"},{"stage":"seal","stageUuid":"0651c890-ac5b-8284-9907-0b2ea9502fb7"},{"stage":"uuid","stageUuid":"46da241d-e534-8fe5-9bb7-919deae9a765"}],"trinity":{"code":0,"form":1,"proof":0}}
