{"_doNotEdit":"run pnpm readme to regenerate; pnpm computed:check to verify","_generated":"src/readme/index.ts","atomPath":"memory","bondsIn":31,"bondsOut":38,"boundaryUuid":"a34b1a22-051a-87cf-92c9-73e1ce0ece5f","computationUuid":"4f1c7582-7a24-8b03-a97a-424fa357be8c","contentUuid":"6ae6141f-e444-8080-b736-230aa580d6c0","escapes":[],"exports":["memory"],"folded":true,"horo":2,"imports":["akashic","collapse","diamond","law","memory","merge","quantum","requirements","seal","sti","thought"],"kind":"atom","links":["akashic","architecture","collapse","diamond","law","memory","merge","quantum","requirements","seal","session","sti","thought"],"linksResolved":17,"linksTotal":17,"measure":"share","stages":[{"stage":"path","stageUuid":"d59a38cc-4d56-8168-bec3-c179f2673238"},{"stage":"trinity","stageUuid":"b468bc89-f81a-824a-83bf-e8b16ff64712"},{"stage":"boundary","stageUuid":"0bce9b01-3b27-88de-ab38-c3b8c5cff4bc"},{"stage":"links","stageUuid":"7871c9be-3b9d-80f8-9295-c859219bc341"},{"stage":"horo","stageUuid":"c68169a0-9148-89de-b5d3-5348c5e7e405"},{"stage":"seal","stageUuid":"06fb6ea6-ed60-85ba-bff9-892cf2731774"},{"stage":"uuid","stageUuid":"1c74c855-46d7-89eb-9853-ef9073a873a7"}],"trinity":{"code":0,"form":1,"proof":0}}
