{"_doNotEdit":"run pnpm readme to regenerate; pnpm computed:check to verify","_generated":"src/readme/index.ts","atomPath":"network","bondsIn":4,"bondsOut":2,"boundaryUuid":"50ecb2f2-e310-8b8f-b5aa-25d210074aaf","computationUuid":"d08e0889-0efb-82bf-bb61-a7ab514cc943","contentUuid":"18e90d15-d129-8eed-86f3-e07420a16cd2","escapes":[],"exports":["network"],"folded":true,"horo":2,"imports":["bottleneck","breath","cohort","competition","connections","decentralization","desire","diffusion","ecosystem","engagement","habit","links","market","mass","merge","network","power"],"kind":"atom","links":["bottleneck","breath","cohort","competition","connections","decentralization","desire","diffusion","ecosystem","engagement","habit","links","market","mass","merge","network","power"],"linksResolved":29,"linksTotal":29,"measure":"share","stages":[{"stage":"path","stageUuid":"3c130c91-56ac-8636-85f4-89f131fa70df"},{"stage":"trinity","stageUuid":"bad3559a-5826-8d53-890e-2e2d75a1b440"},{"stage":"boundary","stageUuid":"00efb141-8264-80d9-992e-1a0d4a286ce5"},{"stage":"links","stageUuid":"050b6296-eb3f-8725-a2bb-9308e063d8f5"},{"stage":"horo","stageUuid":"8a51e12d-0c4b-873e-ab81-9f22bd250a87"},{"stage":"seal","stageUuid":"00086adc-14fe-80d4-a8e9-4948c9f6cc0f"},{"stage":"uuid","stageUuid":"a618e0fc-423c-8190-854a-3a04aece0ef4"}],"trinity":{"code":0,"form":1,"proof":0}}
